UI_files/SAM_V2.ui
model/empty.txt
napari_samv2/__init__.py
napari_samv2/_version.py
napari_samv2/_widget.py
napari_samv2/napari.yaml
napari_samv2/_tests/__init__.py
napari_samv2/_tests/test_widget.py
napari_samv2-0.1.3.dist-info/licenses/LICENSE
pipelines/samv2/Samv2_pipeline_handler.py
napari_samv2-0.1.3.dist-info/METADATA
napari_samv2-0.1.3.dist-info/WHEEL
napari_samv2-0.1.3.dist-info/entry_points.txt
napari_samv2-0.1.3.dist-info/top_level.txt
napari_samv2-0.1.3.dist-info/RECORD
