Metadata-Version: 2.4
Name: napari-samv2
Version: 0.1.3
Summary: Napari plugin for segment anything version 2 model from meta. Plugin primarily useful for segmenting 3d volumetric data or 3d time series data. 
Author: Krishnan Venkataraman
Author-email: krishvraman95@gmail.com
License: 
Project-URL: Bug Tracker, https://github.com/Krishvraman/napari-SAMV2/issues
Project-URL: Documentation, https://github.com/Krishvraman/napari-SAMV2#README.md
Project-URL: Source Code, https://github.com/Krishvraman/napari-SAMV2
Project-URL: User Support, https://github.com/Krishvraman/napari-SAMV2/issues
Classifier: Development Status :: 2 - Pre-Alpha
Classifier: Framework :: napari
Classifier: Intended Audience :: Developers
Classifier: License :: OSI Approved :: BSD License
Classifier: Operating System :: OS Independent
Classifier: Programming Language :: Python
Classifier: Programming Language :: Python :: 3
Classifier: Programming Language :: Python :: 3 :: Only
Classifier: Programming Language :: Python :: 3.9
Classifier: Programming Language :: Python :: 3.10
Classifier: Programming Language :: Python :: 3.11
Classifier: Programming Language :: Python :: 3.12
Classifier: Topic :: Scientific/Engineering :: Image Processing
Requires-Python: >=3.9
License-File: LICENSE
Requires-Dist: numpy
Requires-Dist: magicgui
Requires-Dist: qtpy
Requires-Dist: scikit-image
Provides-Extra: testing
Requires-Dist: tox; extra == "testing"
Requires-Dist: pytest; extra == "testing"
Requires-Dist: pytest-cov; extra == "testing"
Requires-Dist: pytest-qt; extra == "testing"
Requires-Dist: napari; extra == "testing"
Requires-Dist: pyqt5; extra == "testing"
Requires-Dist: numpy; extra == "testing"
Dynamic: license-file
